spcqe/__init__.py
spcqe/_version.py
spcqe/extrapolate_asymptotic.py
spcqe/functions.py
spcqe/quantiles.py
spcqe/solvers.py
spcqe/__pycache__/__init__.cpython-38.pyc
spcqe/__pycache__/__init__.cpython-39.pyc
spcqe/__pycache__/functions.cpython-38.pyc
spcqe/__pycache__/functions.cpython-39.pyc
spcqe-0.3.0.dist-info/LICENSE
spcqe-0.3.0.dist-info/METADATA
spcqe-0.3.0.dist-info/WHEEL
spcqe-0.3.0.dist-info/top_level.txt
spcqe-0.3.0.dist-info/RECORD
