Metadata-Version: 2.2
Name: spcqe
Version: 0.3.0
Summary: Smooth periodic consistent quantile estimation
Author-email: Mehmet Giray Ogut <giray98@stanford.edu>, Aramis Dufour <adufour@stanford.edu>, Bennet Meyers <bennetm@stanford.edu>
License: BSD 2-Clause License
Project-URL: Homepage, https://github.com/cvxgrp/spcqe
Project-URL: Bug Tracker, https://github.com/cvxgrp/spcqe/issues
Classifier: License :: OSI Approved :: BSD License
Classifier: Natural Language :: English
Classifier: Programming Language :: Python :: 3 :: Only
Classifier: Programming Language :: Python :: 3.9
Classifier: Programming Language :: Python :: 3.10
Classifier: Programming Language :: Python :: 3.11
Classifier: Programming Language :: Python :: 3.12
Classifier: Intended Audience :: Science/Research
Classifier: Topic :: Scientific/Engineering
Requires-Python: >=3.9
License-File: LICENSE
Requires-Dist: numpy
Requires-Dist: cvxpy
Requires-Dist: scikit-learn
Requires-Dist: tqdm
Requires-Dist: sig-decomp
